lyrics_client/__init__.py
lyrics_client/classes/__init__.py
lyrics_client/classes/clients/__init__.py
lyrics_client/classes/clients/abstract_lyrics_client.py
lyrics_client/classes/clients/azlyrics_lyrics_client.py
lyrics_client/classes/clients/genius_lyrics_client.py
lyrics_client/classes/clients/musixmatch_lyrics_client.py
lyrics_client/classes/fetch_lyrics_command.py
lyrics_client/classes/fetch_lyrics_result.py
lyrics_client/di/__init__.py
lyrics_client/di/dependency_injector.py
lyrics_client/errors/__init__.py
lyrics_client/errors/bad_format_error.py
lyrics_client/errors/bad_title_match_error.py
lyrics_client/errors/no_result_error.py
lyrics_client/interfaces/__init__.py
lyrics_client/interfaces/base_lyrics_client.py
lyrics_client/main.py
lyrics_client/py.typed
lyrics_client-0.0.4.dist-info/LICENSE
lyrics_client-0.0.4.dist-info/METADATA
lyrics_client-0.0.4.dist-info/WHEEL
lyrics_client-0.0.4.dist-info/RECORD
