Metadata-Version: 2.1
Name: lyrics-client
Version: 0.0.4
Summary: A generic client to fetch lyrics from a song's data
Home-page: https://github.com/Billuc/lyrics-client
License: MIT
Keywords: lyrics client,lyrics,python,genius,azlyrics, musixmatch
Author: Billuc
Author-email: billuc@hotmail.fr
Requires-Python: >=3.9,<4.0
Classifier: Intended Audience :: End Users/Desktop
Classifier: License :: OSI Approved :: MIT License
Classifier: Programming Language :: Python
Classifier: Programming Language :: Python :: 3
Classifier: Programming Language :: Python :: 3.9
Classifier: Programming Language :: Python :: 3.10
Classifier: Programming Language :: Python :: 3.11
Classifier: Topic :: Multimedia
Classifier: Topic :: Multimedia :: Sound/Audio
Classifier: Topic :: Utilities
Requires-Dist: beautifulsoup4 (>=4.12.2,<5.0.0)
Requires-Dist: python-slugify (>=8.0.1,<9.0.0)
Requires-Dist: rapidfuzz (>=3.1.1,<4.0.0)
Requires-Dist: requests (>=2.31.0,<3.0.0)
Requires-Dist: taipan-di (==0.0.7)
Project-URL: Documentation, https://github.com/Billuc/lyrics-client
Project-URL: Repository, https://github.com/Billuc/lyrics-client
